pytkanim/__init__.py
pytkanim/Animations/AnimateX.py
pytkanim/Animations/AnimateY.py
pytkanim/Animations/__init__.py
pytkanim/CustomAnimations/NormalAnimHeight.py
pytkanim/CustomAnimations/NormalAnimWidth.py
pytkanim/CustomAnimations/NormalAnimX.py
pytkanim/CustomAnimations/NormalAnimY.py
pytkanim/CustomAnimations/SlowAnimX.py
pytkanim/CustomAnimations/SlowAnimY.py
pytkanim/CustomAnimations/__init__.py
pytkanim/__easingfunctionsX__/__init__.py
pytkanim/__easingfunctionsX__/ease_in_sine.py
pytkanim/__easingfunctionsY__/__init__.py
pytkanim/__easingfunctionsY__/ease_in_sine.py
PyTkAnim-1.0.2.dist-info/LICENSE.txt
PyTkAnim-1.0.2.dist-info/METADATA
PyTkAnim-1.0.2.dist-info/WHEEL
PyTkAnim-1.0.2.dist-info/entry_points.txt
PyTkAnim-1.0.2.dist-info/top_level.txt
PyTkAnim-1.0.2.dist-info/RECORD
