Metadata-Version: 2.1
Name: PyTkAnim
Version: 1.0.2
Summary: PyTkAnim is extension for tkinter that provides animator and simple usage.
Home-page: https://github.com/carlFandino
Author: Carl Gian D Fandiño
Author-email: giancarl.fandino@gmail.com
License: MIT
Project-URL: Source, https://github.com/carlFandino/pytkanim-1.0.2
Platform: UNKNOWN
Classifier: License :: OSI Approved :: MIT License
Classifier: Programming Language :: Python :: 3
Classifier: Programming Language :: Python :: 3.7
Classifier: Topic :: Software Development :: User Interfaces
Classifier: Natural Language :: English
License-File: LICENSE.txt
